marathon_matches_manager/__init__.py
marathon_matches_manager/const.py
marathon_matches_manager/generate_template.py
marathon_matches_manager/m3.py
marathon_matches_manager/static/bundle.js
marathon_matches_manager/templates/index.html
marathon_matches_manager-0.1.1.dist-info/entry_points.txt
marathon_matches_manager-0.1.1.dist-info/WHEEL
marathon_matches_manager-0.1.1.dist-info/METADATA
marathon_matches_manager-0.1.1.dist-info/RECORD
